{
  "computed_at": "2026-06-05 09:40:49 IST",
  "spot": 23472.85,
  "expiry": "09-Jun-2026",
  "net_gex": 4630020175.3,
  "flip_point": null,
  "regime": "PINNING",
  "interpretation": "Net GEX +4,630,020,175: dealers will BUY dips & SELL rallies (price-pinning near N/A)",
  "strikes": [
    {
      "strike": 21100.0,
      "ce_gex": 0,
      "pe_gex": 405959475.42,
      "net_gex": 405959475.42,
      "ce_iv": null,
      "pe_iv": 36.72
    },
    {
      "strike": 21150.0,
      "ce_gex": 0,
      "pe_gex": 11269741.15,
      "net_gex": 11269741.15,
      "ce_iv": null,
      "pe_iv": 36.18
    },
    {
      "strike": 21200.0,
      "ce_gex": 0,
      "pe_gex": 84101540.63,
      "net_gex": 84101540.63,
      "ce_iv": null,
      "pe_iv": 35.25
    },
    {
      "strike": 21250.0,
      "ce_gex": 0,
      "pe_gex": 5868733.16,
      "net_gex": 5868733.16,
      "ce_iv": null,
      "pe_iv": 34.71
    },
    {
      "strike": 21300.0,
      "ce_gex": 0,
      "pe_gex": 40566801.06,
      "net_gex": 40566801.06,
      "ce_iv": null,
      "pe_iv": 34.16
    },
    {
      "strike": 21350.0,
      "ce_gex": 0,
      "pe_gex": 4771886.74,
      "net_gex": 4771886.74,
      "ce_iv": null,
      "pe_iv": 33.76
    },
    {
      "strike": 21400.0,
      "ce_gex": 0,
      "pe_gex": 42318033.37,
      "net_gex": 42318033.37,
      "ce_iv": null,
      "pe_iv": 33.02
    },
    {
      "strike": 21450.0,
      "ce_gex": 0,
      "pe_gex": 10355429.3,
      "net_gex": 10355429.3,
      "ce_iv": null,
      "pe_iv": 32.58
    },
    {
      "strike": 21500.0,
      "ce_gex": 0,
      "pe_gex": 556889775.78,
      "net_gex": 556889775.78,
      "ce_iv": null,
      "pe_iv": 31.97
    },
    {
      "strike": 21550.0,
      "ce_gex": 0,
      "pe_gex": 14761353.77,
      "net_gex": 14761353.77,
      "ce_iv": null,
      "pe_iv": 31.08
    },
    {
      "strike": 21600.0,
      "ce_gex": 0,
      "pe_gex": 64840866.37,
      "net_gex": 64840866.37,
      "ce_iv": null,
      "pe_iv": 30.33
    },
    {
      "strike": 21650.0,
      "ce_gex": 0,
      "pe_gex": 19219567.44,
      "net_gex": 19219567.44,
      "ce_iv": null,
      "pe_iv": 29.85
    },
    {
      "strike": 21700.0,
      "ce_gex": 0,
      "pe_gex": 85704652.98,
      "net_gex": 85704652.98,
      "ce_iv": null,
      "pe_iv": 29.09
    },
    {
      "strike": 21750.0,
      "ce_gex": 0,
      "pe_gex": 19303125.81,
      "net_gex": 19303125.81,
      "ce_iv": null,
      "pe_iv": 28.46
    },
    {
      "strike": 21800.0,
      "ce_gex": 0,
      "pe_gex": 234198406.01,
      "net_gex": 234198406.01,
      "ce_iv": null,
      "pe_iv": 27.82
    },
    {
      "strike": 21850.0,
      "ce_gex": 0,
      "pe_gex": 33317790.91,
      "net_gex": 33317790.91,
      "ce_iv": null,
      "pe_iv": 27.28
    },
    {
      "strike": 21900.0,
      "ce_gex": 0,
      "pe_gex": 321323824.46,
      "net_gex": 321323824.46,
      "ce_iv": null,
      "pe_iv": 26.51
    },
    {
      "strike": 21950.0,
      "ce_gex": 0,
      "pe_gex": 62990476.16,
      "net_gex": 62990476.16,
      "ce_iv": null,
      "pe_iv": 26.23
    },
    {
      "strike": 22000.0,
      "ce_gex": -16060205.14,
      "pe_gex": 1527593128.54,
      "net_gex": 1511532923.41,
      "ce_iv": 33.1,
      "pe_iv": 25.71
    },
    {
      "strike": 22050.0,
      "ce_gex": 0,
      "pe_gex": 53314077.5,
      "net_gex": 53314077.5,
      "ce_iv": null,
      "pe_iv": 25.0
    },
    {
      "strike": 22100.0,
      "ce_gex": 0,
      "pe_gex": 346485773.53,
      "net_gex": 346485773.53,
      "ce_iv": null,
      "pe_iv": 24.45
    },
    {
      "strike": 22150.0,
      "ce_gex": 0,
      "pe_gex": 75925008.0,
      "net_gex": 75925008.0,
      "ce_iv": null,
      "pe_iv": 23.79
    },
    {
      "strike": 22200.0,
      "ce_gex": 0,
      "pe_gex": 792984691.88,
      "net_gex": 792984691.88,
      "ce_iv": null,
      "pe_iv": 23.26
    },
    {
      "strike": 22250.0,
      "ce_gex": 0,
      "pe_gex": 394578796.62,
      "net_gex": 394578796.62,
      "ce_iv": null,
      "pe_iv": 22.7
    },
    {
      "strike": 22300.0,
      "ce_gex": 0,
      "pe_gex": 1139373722.38,
      "net_gex": 1139373722.38,
      "ce_iv": null,
      "pe_iv": 22.16
    },
    {
      "strike": 22350.0,
      "ce_gex": 0,
      "pe_gex": 526561259.15,
      "net_gex": 526561259.15,
      "ce_iv": null,
      "pe_iv": 21.74
    },
    {
      "strike": 22400.0,
      "ce_gex": 0,
      "pe_gex": 1283466944.41,
      "net_gex": 1283466944.41,
      "ce_iv": null,
      "pe_iv": 21.17
    },
    {
      "strike": 22450.0,
      "ce_gex": -110416.91,
      "pe_gex": 596280085.19,
      "net_gex": 596169668.29,
      "ce_iv": 18.4,
      "pe_iv": 20.61
    },
    {
      "strike": 22500.0,
      "ce_gex": -156797570.58,
      "pe_gex": 6639756993.16,
      "net_gex": 6482959422.58,
      "ce_iv": 25.29,
      "pe_iv": 20.13
    },
    {
      "strike": 22550.0,
      "ce_gex": -2032491.73,
      "pe_gex": 877609423.86,
      "net_gex": 875576932.13,
      "ce_iv": 24.38,
      "pe_iv": 19.52
    },
    {
      "strike": 22600.0,
      "ce_gex": -39871576.0,
      "pe_gex": 2605716096.4,
      "net_gex": 2565844520.4,
      "ce_iv": 28.36,
      "pe_iv": 19.03
    },
    {
      "strike": 22650.0,
      "ce_gex": -4231064.38,
      "pe_gex": 1554462251.9,
      "net_gex": 1550231187.52,
      "ce_iv": 21.12,
      "pe_iv": 18.54
    },
    {
      "strike": 22700.0,
      "ce_gex": -36698256.18,
      "pe_gex": 3793980027.54,
      "net_gex": 3757281771.36,
      "ce_iv": 21.82,
      "pe_iv": 18.1
    },
    {
      "strike": 22750.0,
      "ce_gex": -15234901.7,
      "pe_gex": 1827076750.78,
      "net_gex": 1811841849.08,
      "ce_iv": 21.38,
      "pe_iv": 17.73
    },
    {
      "strike": 22800.0,
      "ce_gex": -130552761.63,
      "pe_gex": 6368755546.42,
      "net_gex": 6238202784.79,
      "ce_iv": 20.88,
      "pe_iv": 17.38
    },
    {
      "strike": 22850.0,
      "ce_gex": -42576692.15,
      "pe_gex": 2380088051.11,
      "net_gex": 2337511358.96,
      "ce_iv": 21.33,
      "pe_iv": 17.05
    },
    {
      "strike": 22900.0,
      "ce_gex": -188162462.48,
      "pe_gex": 8590111111.27,
      "net_gex": 8401948648.8,
      "ce_iv": 19.37,
      "pe_iv": 16.77
    },
    {
      "strike": 22950.0,
      "ce_gex": -66857332.27,
      "pe_gex": 3598784130.7,
      "net_gex": 3531926798.43,
      "ce_iv": 18.76,
      "pe_iv": 16.54
    },
    {
      "strike": 23000.0,
      "ce_gex": -1749216772.67,
      "pe_gex": 25072077504.21,
      "net_gex": 23322860731.54,
      "ce_iv": 19.28,
      "pe_iv": 16.33
    },
    {
      "strike": 23050.0,
      "ce_gex": -115036018.04,
      "pe_gex": 6568169937.99,
      "net_gex": 6453133919.95,
      "ce_iv": 18.97,
      "pe_iv": 16.09
    },
    {
      "strike": 23100.0,
      "ce_gex": -1041647382.3,
      "pe_gex": 14213566477.7,
      "net_gex": 13171919095.39,
      "ce_iv": 18.56,
      "pe_iv": 15.94
    },
    {
      "strike": 23150.0,
      "ce_gex": -528908793.72,
      "pe_gex": 16745245277.4,
      "net_gex": 16216336483.68,
      "ce_iv": 18.0,
      "pe_iv": 15.74
    },
    {
      "strike": 23200.0,
      "ce_gex": -4393804704.89,
      "pe_gex": 25858941914.97,
      "net_gex": 21465137210.07,
      "ce_iv": 17.93,
      "pe_iv": 15.62
    },
    {
      "strike": 23250.0,
      "ce_gex": -2588446370.61,
      "pe_gex": 15889642008.2,
      "net_gex": 13301195637.6,
      "ce_iv": 17.56,
      "pe_iv": 15.49
    },
    {
      "strike": 23300.0,
      "ce_gex": -18891848032.48,
      "pe_gex": 47286021773.24,
      "net_gex": 28394173740.76,
      "ce_iv": 17.39,
      "pe_iv": 15.37
    },
    {
      "strike": 23350.0,
      "ce_gex": -6758304428.63,
      "pe_gex": 20401611822.76,
      "net_gex": 13643307394.13,
      "ce_iv": 17.11,
      "pe_iv": 15.27
    },
    {
      "strike": 23400.0,
      "ce_gex": -23961498649.41,
      "pe_gex": 45019170434.9,
      "net_gex": 21057671785.49,
      "ce_iv": 16.94,
      "pe_iv": 15.18
    },
    {
      "strike": 23450.0,
      "ce_gex": -23134802788.14,
      "pe_gex": 32698825334.91,
      "net_gex": 9564022546.78,
      "ce_iv": 16.82,
      "pe_iv": 15.06
    },
    {
      "strike": 23500.0,
      "ce_gex": -60711078574.19,
      "pe_gex": 54832273911.82,
      "net_gex": -5878804662.37,
      "ce_iv": 16.65,
      "pe_iv": 14.9
    },
    {
      "strike": 23550.0,
      "ce_gex": -16773752605.97,
      "pe_gex": 9857191572.62,
      "net_gex": -6916561033.36,
      "ce_iv": 16.54,
      "pe_iv": 14.77
    },
    {
      "strike": 23600.0,
      "ce_gex": -31440949636.01,
      "pe_gex": 15513115309.4,
      "net_gex": -15927834326.61,
      "ce_iv": 16.47,
      "pe_iv": 14.63
    },
    {
      "strike": 23650.0,
      "ce_gex": -13647848262.68,
      "pe_gex": 2344013974.83,
      "net_gex": -11303834287.85,
      "ce_iv": 16.4,
      "pe_iv": 14.45
    },
    {
      "strike": 23700.0,
      "ce_gex": -31729234126.79,
      "pe_gex": 12530515481.15,
      "net_gex": -19198718645.64,
      "ce_iv": 16.37,
      "pe_iv": 14.24
    },
    {
      "strike": 23750.0,
      "ce_gex": -11291935900.65,
      "pe_gex": 1078970059.75,
      "net_gex": -10212965840.9,
      "ce_iv": 16.34,
      "pe_iv": 14.21
    },
    {
      "strike": 23800.0,
      "ce_gex": -27067697937.55,
      "pe_gex": 3441259302.16,
      "net_gex": -23626438635.39,
      "ce_iv": 16.31,
      "pe_iv": 13.83
    },
    {
      "strike": 23850.0,
      "ce_gex": -8167821493.35,
      "pe_gex": 453408228.16,
      "net_gex": -7714413265.18,
      "ce_iv": 16.4,
      "pe_iv": 14.24
    },
    {
      "strike": 23900.0,
      "ce_gex": -14692375390.17,
      "pe_gex": 1514624556.31,
      "net_gex": -13177750833.85,
      "ce_iv": 16.47,
      "pe_iv": 14.71
    },
    {
      "strike": 23950.0,
      "ce_gex": -6401477111.72,
      "pe_gex": 336823555.32,
      "net_gex": -6064653556.4,
      "ce_iv": 16.6,
      "pe_iv": 15.2
    },
    {
      "strike": 24000.0,
      "ce_gex": -38228896736.4,
      "pe_gex": 0,
      "net_gex": -38228896736.4,
      "ce_iv": 16.77,
      "pe_iv": null
    },
    {
      "strike": 24050.0,
      "ce_gex": -4094744817.05,
      "pe_gex": 0,
      "net_gex": -4094744817.05,
      "ce_iv": 16.89,
      "pe_iv": null
    },
    {
      "strike": 24100.0,
      "ce_gex": -7871101128.29,
      "pe_gex": 0,
      "net_gex": -7871101128.29,
      "ce_iv": 17.05,
      "pe_iv": null
    },
    {
      "strike": 24150.0,
      "ce_gex": -2881978045.78,
      "pe_gex": 0,
      "net_gex": -2881978045.78,
      "ce_iv": 17.26,
      "pe_iv": null
    },
    {
      "strike": 24200.0,
      "ce_gex": -10065120397.24,
      "pe_gex": 0,
      "net_gex": -10065120397.24,
      "ce_iv": 17.46,
      "pe_iv": null
    },
    {
      "strike": 24250.0,
      "ce_gex": -1538764463.07,
      "pe_gex": 0,
      "net_gex": -1538764463.07,
      "ce_iv": 17.72,
      "pe_iv": null
    },
    {
      "strike": 24300.0,
      "ce_gex": -3875489456.62,
      "pe_gex": 0,
      "net_gex": -3875489456.62,
      "ce_iv": 17.97,
      "pe_iv": null
    },
    {
      "strike": 24350.0,
      "ce_gex": -1323656605.59,
      "pe_gex": 0,
      "net_gex": -1323656605.59,
      "ce_iv": 18.31,
      "pe_iv": null
    },
    {
      "strike": 24400.0,
      "ce_gex": -3324814289.39,
      "pe_gex": 0,
      "net_gex": -3324814289.39,
      "ce_iv": 18.64,
      "pe_iv": null
    },
    {
      "strike": 24450.0,
      "ce_gex": -584803989.21,
      "pe_gex": 0,
      "net_gex": -584803989.21,
      "ce_iv": 18.9,
      "pe_iv": null
    },
    {
      "strike": 24500.0,
      "ce_gex": -5063190256.77,
      "pe_gex": 0,
      "net_gex": -5063190256.77,
      "ce_iv": 19.31,
      "pe_iv": null
    },
    {
      "strike": 24550.0,
      "ce_gex": -615888993.6,
      "pe_gex": 0,
      "net_gex": -615888993.6,
      "ce_iv": 19.65,
      "pe_iv": null
    },
    {
      "strike": 24600.0,
      "ce_gex": -1525771862.03,
      "pe_gex": 0,
      "net_gex": -1525771862.03,
      "ce_iv": 20.0,
      "pe_iv": null
    },
    {
      "strike": 24650.0,
      "ce_gex": -262073882.45,
      "pe_gex": 0,
      "net_gex": -262073882.45,
      "ce_iv": 20.34,
      "pe_iv": null
    },
    {
      "strike": 24700.0,
      "ce_gex": -1248565663.03,
      "pe_gex": 0,
      "net_gex": -1248565663.03,
      "ce_iv": 20.61,
      "pe_iv": null
    },
    {
      "strike": 24750.0,
      "ce_gex": -282982178.11,
      "pe_gex": 0,
      "net_gex": -282982178.11,
      "ce_iv": 20.99,
      "pe_iv": null
    },
    {
      "strike": 24800.0,
      "ce_gex": -1160629546.98,
      "pe_gex": 0,
      "net_gex": -1160629546.98,
      "ce_iv": 21.32,
      "pe_iv": null
    },
    {
      "strike": 24850.0,
      "ce_gex": -164742188.93,
      "pe_gex": 0,
      "net_gex": -164742188.93,
      "ce_iv": 21.76,
      "pe_iv": null
    },
    {
      "strike": 24900.0,
      "ce_gex": -558523480.94,
      "pe_gex": 0,
      "net_gex": -558523480.94,
      "ce_iv": 22.17,
      "pe_iv": null
    },
    {
      "strike": 24950.0,
      "ce_gex": -182123713.23,
      "pe_gex": 0,
      "net_gex": -182123713.23,
      "ce_iv": 22.64,
      "pe_iv": null
    },
    {
      "strike": 25000.0,
      "ce_gex": -1592594773.55,
      "pe_gex": 0,
      "net_gex": -1592594773.55,
      "ce_iv": 23.3,
      "pe_iv": null
    },
    {
      "strike": 25050.0,
      "ce_gex": -113035204.26,
      "pe_gex": 0,
      "net_gex": -113035204.26,
      "ce_iv": 23.62,
      "pe_iv": null
    },
    {
      "strike": 25100.0,
      "ce_gex": -230425466.87,
      "pe_gex": 0,
      "net_gex": -230425466.87,
      "ce_iv": 24.27,
      "pe_iv": null
    },
    {
      "strike": 25150.0,
      "ce_gex": -62572527.78,
      "pe_gex": 0,
      "net_gex": -62572527.78,
      "ce_iv": 24.67,
      "pe_iv": null
    },
    {
      "strike": 25200.0,
      "ce_gex": -295370588.16,
      "pe_gex": 0,
      "net_gex": -295370588.16,
      "ce_iv": 25.17,
      "pe_iv": null
    },
    {
      "strike": 25250.0,
      "ce_gex": -52003826.88,
      "pe_gex": 0,
      "net_gex": -52003826.88,
      "ce_iv": 25.65,
      "pe_iv": null
    },
    {
      "strike": 25300.0,
      "ce_gex": -169265927.25,
      "pe_gex": 0,
      "net_gex": -169265927.25,
      "ce_iv": 26.28,
      "pe_iv": null
    },
    {
      "strike": 25350.0,
      "ce_gex": -28967221.5,
      "pe_gex": 0,
      "net_gex": -28967221.5,
      "ce_iv": 26.9,
      "pe_iv": null
    },
    {
      "strike": 25400.0,
      "ce_gex": -60754566.78,
      "pe_gex": 0,
      "net_gex": -60754566.78,
      "ce_iv": 27.36,
      "pe_iv": null
    },
    {
      "strike": 25450.0,
      "ce_gex": -17629146.18,
      "pe_gex": 0,
      "net_gex": -17629146.18,
      "ce_iv": 27.64,
      "pe_iv": null
    },
    {
      "strike": 25500.0,
      "ce_gex": -410470348.21,
      "pe_gex": 0,
      "net_gex": -410470348.21,
      "ce_iv": 28.42,
      "pe_iv": null
    },
    {
      "strike": 25550.0,
      "ce_gex": -21293110.48,
      "pe_gex": 0,
      "net_gex": -21293110.48,
      "ce_iv": 29.02,
      "pe_iv": null
    },
    {
      "strike": 25600.0,
      "ce_gex": -48364882.25,
      "pe_gex": 0,
      "net_gex": -48364882.25,
      "ce_iv": 29.44,
      "pe_iv": null
    },
    {
      "strike": 25650.0,
      "ce_gex": -7341660.57,
      "pe_gex": 0,
      "net_gex": -7341660.57,
      "ce_iv": 30.04,
      "pe_iv": null
    },
    {
      "strike": 25700.0,
      "ce_gex": -23363274.57,
      "pe_gex": 0,
      "net_gex": -23363274.57,
      "ce_iv": 30.44,
      "pe_iv": null
    },
    {
      "strike": 25750.0,
      "ce_gex": -5925079.52,
      "pe_gex": 0,
      "net_gex": -5925079.52,
      "ce_iv": 31.02,
      "pe_iv": null
    },
    {
      "strike": 25800.0,
      "ce_gex": -23532692.68,
      "pe_gex": 0,
      "net_gex": -23532692.68,
      "ce_iv": 31.17,
      "pe_iv": null
    },
    {
      "strike": 25850.0,
      "ce_gex": -11001959.15,
      "pe_gex": 0,
      "net_gex": -11001959.15,
      "ce_iv": 31.98,
      "pe_iv": null
    },
    {
      "strike": 25900.0,
      "ce_gex": -11851327.57,
      "pe_gex": 0,
      "net_gex": -11851327.57,
      "ce_iv": 32.33,
      "pe_iv": null
    },
    {
      "strike": 25950.0,
      "ce_gex": -4270929.32,
      "pe_gex": 0,
      "net_gex": -4270929.32,
      "ce_iv": 32.9,
      "pe_iv": null
    },
    {
      "strike": 26000.0,
      "ce_gex": -124852393.22,
      "pe_gex": 0,
      "net_gex": -124852393.22,
      "ce_iv": 33.47,
      "pe_iv": null
    },
    {
      "strike": 26050.0,
      "ce_gex": -4641277.66,
      "pe_gex": 0,
      "net_gex": -4641277.66,
      "ce_iv": 33.51,
      "pe_iv": null
    },
    {
      "strike": 26100.0,
      "ce_gex": -55853023.16,
      "pe_gex": 0,
      "net_gex": -55853023.16,
      "ce_iv": 33.77,
      "pe_iv": null
    }
  ]
}