{
  "computed_at": "2026-04-29 10:50:46 IST",
  "spot": 24266.55,
  "expiry": "05-May-2026",
  "net_gex": 63109200596.3,
  "flip_point": null,
  "regime": "PINNING",
  "interpretation": "Net GEX +63,109,200,596: dealers will BUY dips & SELL rallies (price-pinning near N/A)",
  "strikes": [
    {
      "strike": 20100.0,
      "ce_gex": 0,
      "pe_gex": 16242985.72,
      "net_gex": 16242985.72,
      "ce_iv": null,
      "pe_iv": 49.34
    },
    {
      "strike": 20150.0,
      "ce_gex": 0,
      "pe_gex": 1512214.45,
      "net_gex": 1512214.45,
      "ce_iv": null,
      "pe_iv": 49.37
    },
    {
      "strike": 20200.0,
      "ce_gex": 0,
      "pe_gex": 1041823.26,
      "net_gex": 1041823.26,
      "ce_iv": null,
      "pe_iv": 49.33
    },
    {
      "strike": 20250.0,
      "ce_gex": 0,
      "pe_gex": 457490.71,
      "net_gex": 457490.71,
      "ce_iv": null,
      "pe_iv": 48.73
    },
    {
      "strike": 20300.0,
      "ce_gex": 0,
      "pe_gex": 865219.3,
      "net_gex": 865219.3,
      "ce_iv": null,
      "pe_iv": 48.12
    },
    {
      "strike": 20350.0,
      "ce_gex": 0,
      "pe_gex": 384690.73,
      "net_gex": 384690.73,
      "ce_iv": null,
      "pe_iv": 47.52
    },
    {
      "strike": 20400.0,
      "ce_gex": 0,
      "pe_gex": 649322.48,
      "net_gex": 649322.48,
      "ce_iv": null,
      "pe_iv": 47.64
    },
    {
      "strike": 20450.0,
      "ce_gex": 0,
      "pe_gex": 366019.76,
      "net_gex": 366019.76,
      "ce_iv": null,
      "pe_iv": 47.03
    },
    {
      "strike": 20500.0,
      "ce_gex": 0,
      "pe_gex": 14421729.3,
      "net_gex": 14421729.3,
      "ce_iv": null,
      "pe_iv": 46.2
    },
    {
      "strike": 20550.0,
      "ce_gex": 0,
      "pe_gex": 308915.63,
      "net_gex": 308915.63,
      "ce_iv": null,
      "pe_iv": 45.59
    },
    {
      "strike": 20600.0,
      "ce_gex": 0,
      "pe_gex": 247595.77,
      "net_gex": 247595.77,
      "ce_iv": null,
      "pe_iv": 45.21
    },
    {
      "strike": 20650.0,
      "ce_gex": 0,
      "pe_gex": 274457.45,
      "net_gex": 274457.45,
      "ce_iv": null,
      "pe_iv": 45.01
    },
    {
      "strike": 20700.0,
      "ce_gex": 0,
      "pe_gex": 469104.02,
      "net_gex": 469104.02,
      "ce_iv": null,
      "pe_iv": 44.4
    },
    {
      "strike": 20750.0,
      "ce_gex": 0,
      "pe_gex": 499944.11,
      "net_gex": 499944.11,
      "ce_iv": null,
      "pe_iv": 43.99
    },
    {
      "strike": 20800.0,
      "ce_gex": 0,
      "pe_gex": 1289615.37,
      "net_gex": 1289615.37,
      "ce_iv": null,
      "pe_iv": 43.91
    },
    {
      "strike": 20850.0,
      "ce_gex": 0,
      "pe_gex": 299391.36,
      "net_gex": 299391.36,
      "ce_iv": null,
      "pe_iv": 43.3
    },
    {
      "strike": 20900.0,
      "ce_gex": 0,
      "pe_gex": 1685405.22,
      "net_gex": 1685405.22,
      "ce_iv": null,
      "pe_iv": 42.51
    },
    {
      "strike": 20950.0,
      "ce_gex": 0,
      "pe_gex": 580622.45,
      "net_gex": 580622.45,
      "ce_iv": null,
      "pe_iv": 41.9
    },
    {
      "strike": 21000.0,
      "ce_gex": 0,
      "pe_gex": 113472783.34,
      "net_gex": 113472783.34,
      "ce_iv": null,
      "pe_iv": 41.45
    },
    {
      "strike": 21050.0,
      "ce_gex": 0,
      "pe_gex": 380141.63,
      "net_gex": 380141.63,
      "ce_iv": null,
      "pe_iv": 41.15
    },
    {
      "strike": 21100.0,
      "ce_gex": 0,
      "pe_gex": 2463904.18,
      "net_gex": 2463904.18,
      "ce_iv": null,
      "pe_iv": 40.38
    },
    {
      "strike": 21150.0,
      "ce_gex": 0,
      "pe_gex": 239886.41,
      "net_gex": 239886.41,
      "ce_iv": null,
      "pe_iv": 39.92
    },
    {
      "strike": 21200.0,
      "ce_gex": 0,
      "pe_gex": 6307295.66,
      "net_gex": 6307295.66,
      "ce_iv": null,
      "pe_iv": 39.3
    },
    {
      "strike": 21250.0,
      "ce_gex": 0,
      "pe_gex": 619773.02,
      "net_gex": 619773.02,
      "ce_iv": null,
      "pe_iv": 39.24
    },
    {
      "strike": 21300.0,
      "ce_gex": 0,
      "pe_gex": 2466406.86,
      "net_gex": 2466406.86,
      "ce_iv": null,
      "pe_iv": 38.35
    },
    {
      "strike": 21350.0,
      "ce_gex": 0,
      "pe_gex": 382403.33,
      "net_gex": 382403.33,
      "ce_iv": null,
      "pe_iv": 38.25
    },
    {
      "strike": 21400.0,
      "ce_gex": 0,
      "pe_gex": 3893445.78,
      "net_gex": 3893445.78,
      "ce_iv": null,
      "pe_iv": 37.5
    },
    {
      "strike": 21450.0,
      "ce_gex": 0,
      "pe_gex": 1761099.57,
      "net_gex": 1761099.57,
      "ce_iv": null,
      "pe_iv": 37.12
    },
    {
      "strike": 21500.0,
      "ce_gex": 0,
      "pe_gex": 187694534.44,
      "net_gex": 187694534.44,
      "ce_iv": null,
      "pe_iv": 36.38
    },
    {
      "strike": 21550.0,
      "ce_gex": 0,
      "pe_gex": 2504309.64,
      "net_gex": 2504309.64,
      "ce_iv": null,
      "pe_iv": 35.98
    },
    {
      "strike": 21600.0,
      "ce_gex": 0,
      "pe_gex": 14652059.8,
      "net_gex": 14652059.8,
      "ce_iv": null,
      "pe_iv": 35.25
    },
    {
      "strike": 21650.0,
      "ce_gex": 0,
      "pe_gex": 1746326.86,
      "net_gex": 1746326.86,
      "ce_iv": null,
      "pe_iv": 34.95
    },
    {
      "strike": 21700.0,
      "ce_gex": 0,
      "pe_gex": 7627058.52,
      "net_gex": 7627058.52,
      "ce_iv": null,
      "pe_iv": 34.22
    },
    {
      "strike": 21750.0,
      "ce_gex": 0,
      "pe_gex": 2910009.05,
      "net_gex": 2910009.05,
      "ce_iv": null,
      "pe_iv": 33.79
    },
    {
      "strike": 21800.0,
      "ce_gex": 0,
      "pe_gex": 48706922.72,
      "net_gex": 48706922.72,
      "ce_iv": null,
      "pe_iv": 33.26
    },
    {
      "strike": 21850.0,
      "ce_gex": 0,
      "pe_gex": 3413332.71,
      "net_gex": 3413332.71,
      "ce_iv": null,
      "pe_iv": 32.82
    },
    {
      "strike": 21900.0,
      "ce_gex": 0,
      "pe_gex": 26772877.85,
      "net_gex": 26772877.85,
      "ce_iv": null,
      "pe_iv": 32.27
    },
    {
      "strike": 21950.0,
      "ce_gex": 0,
      "pe_gex": 1812579.0,
      "net_gex": 1812579.0,
      "ce_iv": null,
      "pe_iv": 31.64
    },
    {
      "strike": 22000.0,
      "ce_gex": -9390157.93,
      "pe_gex": 438434737.79,
      "net_gex": 429044579.86,
      "ce_iv": 42.72,
      "pe_iv": 31.26
    },
    {
      "strike": 22050.0,
      "ce_gex": 0,
      "pe_gex": 4350528.25,
      "net_gex": 4350528.25,
      "ce_iv": null,
      "pe_iv": 30.54
    },
    {
      "strike": 22100.0,
      "ce_gex": 0,
      "pe_gex": 43030956.78,
      "net_gex": 43030956.78,
      "ce_iv": null,
      "pe_iv": 30.07
    },
    {
      "strike": 22150.0,
      "ce_gex": 0,
      "pe_gex": 21032222.01,
      "net_gex": 21032222.01,
      "ce_iv": null,
      "pe_iv": 29.51
    },
    {
      "strike": 22200.0,
      "ce_gex": 0,
      "pe_gex": 97500966.81,
      "net_gex": 97500966.81,
      "ce_iv": null,
      "pe_iv": 28.87
    },
    {
      "strike": 22250.0,
      "ce_gex": 0,
      "pe_gex": 16729991.77,
      "net_gex": 16729991.77,
      "ce_iv": null,
      "pe_iv": 28.44
    },
    {
      "strike": 22300.0,
      "ce_gex": 0,
      "pe_gex": 109586195.52,
      "net_gex": 109586195.52,
      "ce_iv": null,
      "pe_iv": 27.87
    },
    {
      "strike": 22350.0,
      "ce_gex": -24917.29,
      "pe_gex": 30525881.86,
      "net_gex": 30500964.57,
      "ce_iv": 35.03,
      "pe_iv": 27.48
    },
    {
      "strike": 22400.0,
      "ce_gex": 0,
      "pe_gex": 141055274.75,
      "net_gex": 141055274.75,
      "ce_iv": null,
      "pe_iv": 26.95
    },
    {
      "strike": 22450.0,
      "ce_gex": 0,
      "pe_gex": 48056674.66,
      "net_gex": 48056674.66,
      "ce_iv": null,
      "pe_iv": 26.59
    },
    {
      "strike": 22500.0,
      "ce_gex": 0,
      "pe_gex": 941559722.34,
      "net_gex": 941559722.34,
      "ce_iv": null,
      "pe_iv": 26.14
    },
    {
      "strike": 22550.0,
      "ce_gex": 0,
      "pe_gex": 51748668.56,
      "net_gex": 51748668.56,
      "ce_iv": null,
      "pe_iv": 25.68
    },
    {
      "strike": 22600.0,
      "ce_gex": 0,
      "pe_gex": 276602765.61,
      "net_gex": 276602765.61,
      "ce_iv": null,
      "pe_iv": 25.16
    },
    {
      "strike": 22650.0,
      "ce_gex": 0,
      "pe_gex": 81153481.03,
      "net_gex": 81153481.03,
      "ce_iv": null,
      "pe_iv": 24.76
    },
    {
      "strike": 22700.0,
      "ce_gex": -3518817.38,
      "pe_gex": 448520166.67,
      "net_gex": 445001349.29,
      "ce_iv": 35.3,
      "pe_iv": 24.37
    },
    {
      "strike": 22750.0,
      "ce_gex": 0,
      "pe_gex": 112546888.07,
      "net_gex": 112546888.07,
      "ce_iv": null,
      "pe_iv": 23.92
    },
    {
      "strike": 22800.0,
      "ce_gex": -6496674.35,
      "pe_gex": 943432463.24,
      "net_gex": 936935788.89,
      "ce_iv": 32.26,
      "pe_iv": 23.48
    },
    {
      "strike": 22850.0,
      "ce_gex": 0,
      "pe_gex": 855130608.08,
      "net_gex": 855130608.08,
      "ce_iv": null,
      "pe_iv": 23.12
    },
    {
      "strike": 22900.0,
      "ce_gex": 0,
      "pe_gex": 977410058.74,
      "net_gex": 977410058.74,
      "ce_iv": null,
      "pe_iv": 22.67
    },
    {
      "strike": 22950.0,
      "ce_gex": 0,
      "pe_gex": 240533918.83,
      "net_gex": 240533918.83,
      "ce_iv": null,
      "pe_iv": 22.3
    },
    {
      "strike": 23000.0,
      "ce_gex": -180206651.56,
      "pe_gex": 3741188783.13,
      "net_gex": 3560982131.56,
      "ce_iv": 28.7,
      "pe_iv": 21.87
    },
    {
      "strike": 23050.0,
      "ce_gex": 0,
      "pe_gex": 368721831.0,
      "net_gex": 368721831.0,
      "ce_iv": null,
      "pe_iv": 21.53
    },
    {
      "strike": 23100.0,
      "ce_gex": -10387804.16,
      "pe_gex": 1327712052.21,
      "net_gex": 1317324248.05,
      "ce_iv": 26.56,
      "pe_iv": 21.14
    },
    {
      "strike": 23150.0,
      "ce_gex": -3603077.65,
      "pe_gex": 679146563.93,
      "net_gex": 675543486.28,
      "ce_iv": 23.51,
      "pe_iv": 20.8
    },
    {
      "strike": 23200.0,
      "ce_gex": -20553036.9,
      "pe_gex": 2518977271.5,
      "net_gex": 2498424234.6,
      "ce_iv": 26.14,
      "pe_iv": 20.39
    },
    {
      "strike": 23250.0,
      "ce_gex": -4091519.77,
      "pe_gex": 893293247.3,
      "net_gex": 889201727.53,
      "ce_iv": 25.42,
      "pe_iv": 20.09
    },
    {
      "strike": 23300.0,
      "ce_gex": -63341675.28,
      "pe_gex": 2409055032.19,
      "net_gex": 2345713356.91,
      "ce_iv": 22.66,
      "pe_iv": 19.74
    },
    {
      "strike": 23350.0,
      "ce_gex": -3822911.05,
      "pe_gex": 1008767257.75,
      "net_gex": 1004944346.7,
      "ce_iv": 24.21,
      "pe_iv": 19.4
    },
    {
      "strike": 23400.0,
      "ce_gex": -54469120.6,
      "pe_gex": 2676549759.0,
      "net_gex": 2622080638.4,
      "ce_iv": 23.5,
      "pe_iv": 19.12
    },
    {
      "strike": 23450.0,
      "ce_gex": -12125984.07,
      "pe_gex": 1364102713.02,
      "net_gex": 1351976728.95,
      "ce_iv": 22.46,
      "pe_iv": 18.79
    },
    {
      "strike": 23500.0,
      "ce_gex": -826804212.5,
      "pe_gex": 5721108647.54,
      "net_gex": 4894304435.03,
      "ce_iv": 20.76,
      "pe_iv": 18.52
    },
    {
      "strike": 23550.0,
      "ce_gex": -23944970.88,
      "pe_gex": 1080953470.83,
      "net_gex": 1057008499.95,
      "ce_iv": 20.02,
      "pe_iv": 18.26
    },
    {
      "strike": 23600.0,
      "ce_gex": -157474603.61,
      "pe_gex": 4511329086.51,
      "net_gex": 4353854482.89,
      "ce_iv": 19.4,
      "pe_iv": 17.98
    },
    {
      "strike": 23650.0,
      "ce_gex": -63260358.45,
      "pe_gex": 1975785991.06,
      "net_gex": 1912525632.61,
      "ce_iv": 19.01,
      "pe_iv": 17.74
    },
    {
      "strike": 23700.0,
      "ce_gex": -412709515.63,
      "pe_gex": 6170282895.83,
      "net_gex": 5757573380.19,
      "ce_iv": 19.3,
      "pe_iv": 17.48
    },
    {
      "strike": 23750.0,
      "ce_gex": -129100388.68,
      "pe_gex": 2845305691.39,
      "net_gex": 2716205302.71,
      "ce_iv": 19.03,
      "pe_iv": 17.27
    },
    {
      "strike": 23800.0,
      "ce_gex": -1354506529.86,
      "pe_gex": 10417374178.67,
      "net_gex": 9062867648.8,
      "ce_iv": 18.58,
      "pe_iv": 17.02
    },
    {
      "strike": 23850.0,
      "ce_gex": -259786208.12,
      "pe_gex": 4087660819.98,
      "net_gex": 3827874611.86,
      "ce_iv": 17.96,
      "pe_iv": 16.81
    },
    {
      "strike": 23900.0,
      "ce_gex": -2041935291.72,
      "pe_gex": 12162133068.41,
      "net_gex": 10120197776.69,
      "ce_iv": 18.11,
      "pe_iv": 16.61
    },
    {
      "strike": 23950.0,
      "ce_gex": -626055451.35,
      "pe_gex": 5593349767.28,
      "net_gex": 4967294315.92,
      "ce_iv": 17.89,
      "pe_iv": 16.39
    },
    {
      "strike": 24000.0,
      "ce_gex": -9702646911.4,
      "pe_gex": 32568645513.7,
      "net_gex": 22865998602.3,
      "ce_iv": 17.65,
      "pe_iv": 16.18
    },
    {
      "strike": 24050.0,
      "ce_gex": -3230620325.5,
      "pe_gex": 11086099417.07,
      "net_gex": 7855479091.57,
      "ce_iv": 17.31,
      "pe_iv": 15.99
    },
    {
      "strike": 24100.0,
      "ce_gex": -11344135361.04,
      "pe_gex": 33712527892.45,
      "net_gex": 22368392531.4,
      "ce_iv": 17.17,
      "pe_iv": 15.79
    },
    {
      "strike": 24150.0,
      "ce_gex": -6423153551.52,
      "pe_gex": 15978230881.85,
      "net_gex": 9555077330.33,
      "ce_iv": 16.9,
      "pe_iv": 15.61
    },
    {
      "strike": 24200.0,
      "ce_gex": -18184314140.01,
      "pe_gex": 36113946043.6,
      "net_gex": 17929631903.59,
      "ce_iv": 16.7,
      "pe_iv": 15.42
    },
    {
      "strike": 24250.0,
      "ce_gex": -7915720677.11,
      "pe_gex": 14229412412.07,
      "net_gex": 6313691734.96,
      "ce_iv": 16.44,
      "pe_iv": 15.23
    },
    {
      "strike": 24300.0,
      "ce_gex": -17033612904.64,
      "pe_gex": 22096140828.13,
      "net_gex": 5062527923.49,
      "ce_iv": 16.21,
      "pe_iv": 15.08
    },
    {
      "strike": 24350.0,
      "ce_gex": -6150333851.65,
      "pe_gex": 3535417753.01,
      "net_gex": -2614916098.64,
      "ce_iv": 16.03,
      "pe_iv": 14.86
    },
    {
      "strike": 24400.0,
      "ce_gex": -11636699524.64,
      "pe_gex": 5744518246.34,
      "net_gex": -5892181278.3,
      "ce_iv": 15.89,
      "pe_iv": 14.69
    },
    {
      "strike": 24450.0,
      "ce_gex": -4472170561.85,
      "pe_gex": 1269413381.28,
      "net_gex": -3202757180.57,
      "ce_iv": 15.71,
      "pe_iv": 14.43
    },
    {
      "strike": 24500.0,
      "ce_gex": -22885103863.8,
      "pe_gex": 7132609281.47,
      "net_gex": -15752494582.33,
      "ce_iv": 15.54,
      "pe_iv": 14.28
    },
    {
      "strike": 24550.0,
      "ce_gex": -4585196451.98,
      "pe_gex": 714487099.06,
      "net_gex": -3870709352.92,
      "ce_iv": 15.44,
      "pe_iv": 14.06
    },
    {
      "strike": 24600.0,
      "ce_gex": -9995611542.07,
      "pe_gex": 1170434953.06,
      "net_gex": -8825176589.02,
      "ce_iv": 15.33,
      "pe_iv": 13.86
    },
    {
      "strike": 24650.0,
      "ce_gex": -3726589285.48,
      "pe_gex": 127913327.18,
      "net_gex": -3598675958.3,
      "ce_iv": 15.24,
      "pe_iv": 13.72
    },
    {
      "strike": 24700.0,
      "ce_gex": -7632686307.64,
      "pe_gex": 827931636.98,
      "net_gex": -6804754670.66,
      "ce_iv": 15.14,
      "pe_iv": 13.63
    },
    {
      "strike": 24750.0,
      "ce_gex": -3178224906.28,
      "pe_gex": 53200552.03,
      "net_gex": -3125024354.25,
      "ce_iv": 15.1,
      "pe_iv": 13.53
    },
    {
      "strike": 24800.0,
      "ce_gex": -9079581445.96,
      "pe_gex": 0,
      "net_gex": -9079581445.96,
      "ce_iv": 15.05,
      "pe_iv": null
    },
    {
      "strike": 24850.0,
      "ce_gex": -2230857002.91,
      "pe_gex": 0,
      "net_gex": -2230857002.91,
      "ce_iv": 15.07,
      "pe_iv": null
    },
    {
      "strike": 24900.0,
      "ce_gex": -4523200720.21,
      "pe_gex": 0,
      "net_gex": -4523200720.21,
      "ce_iv": 15.06,
      "pe_iv": null
    },
    {
      "strike": 24950.0,
      "ce_gex": -2367064767.02,
      "pe_gex": 0,
      "net_gex": -2367064767.02,
      "ce_iv": 15.1,
      "pe_iv": null
    },
    {
      "strike": 25000.0,
      "ce_gex": -11900114983.45,
      "pe_gex": 0,
      "net_gex": -11900114983.45,
      "ce_iv": 15.13,
      "pe_iv": null
    },
    {
      "strike": 25050.0,
      "ce_gex": -1133670499.95,
      "pe_gex": 0,
      "net_gex": -1133670499.95,
      "ce_iv": 15.25,
      "pe_iv": null
    },
    {
      "strike": 25100.0,
      "ce_gex": -3945655431.13,
      "pe_gex": 0,
      "net_gex": -3945655431.13,
      "ce_iv": 15.32,
      "pe_iv": null
    },
    {
      "strike": 25150.0,
      "ce_gex": -873786086.66,
      "pe_gex": 0,
      "net_gex": -873786086.66,
      "ce_iv": 15.45,
      "pe_iv": null
    },
    {
      "strike": 25200.0,
      "ce_gex": -3084213858.66,
      "pe_gex": 0,
      "net_gex": -3084213858.66,
      "ce_iv": 15.51,
      "pe_iv": null
    },
    {
      "strike": 25250.0,
      "ce_gex": -508540949.85,
      "pe_gex": 0,
      "net_gex": -508540949.85,
      "ce_iv": 15.72,
      "pe_iv": null
    },
    {
      "strike": 25300.0,
      "ce_gex": -1320768409.53,
      "pe_gex": 0,
      "net_gex": -1320768409.53,
      "ce_iv": 15.88,
      "pe_iv": null
    },
    {
      "strike": 25350.0,
      "ce_gex": -308045903.15,
      "pe_gex": 0,
      "net_gex": -308045903.15,
      "ce_iv": 16.06,
      "pe_iv": null
    },
    {
      "strike": 25400.0,
      "ce_gex": -749044843.08,
      "pe_gex": 0,
      "net_gex": -749044843.08,
      "ce_iv": 16.21,
      "pe_iv": null
    },
    {
      "strike": 25450.0,
      "ce_gex": -318217049.98,
      "pe_gex": 0,
      "net_gex": -318217049.98,
      "ce_iv": 16.43,
      "pe_iv": null
    },
    {
      "strike": 25500.0,
      "ce_gex": -1762024307.32,
      "pe_gex": 0,
      "net_gex": -1762024307.32,
      "ce_iv": 16.62,
      "pe_iv": null
    },
    {
      "strike": 25550.0,
      "ce_gex": -112975878.89,
      "pe_gex": 0,
      "net_gex": -112975878.89,
      "ce_iv": 16.84,
      "pe_iv": null
    },
    {
      "strike": 25600.0,
      "ce_gex": -551631621.61,
      "pe_gex": 0,
      "net_gex": -551631621.61,
      "ce_iv": 16.92,
      "pe_iv": null
    },
    {
      "strike": 25650.0,
      "ce_gex": -90631783.57,
      "pe_gex": 0,
      "net_gex": -90631783.57,
      "ce_iv": 17.04,
      "pe_iv": null
    },
    {
      "strike": 25700.0,
      "ce_gex": -272392556.21,
      "pe_gex": 0,
      "net_gex": -272392556.21,
      "ce_iv": 17.33,
      "pe_iv": null
    },
    {
      "strike": 25750.0,
      "ce_gex": -79299749.22,
      "pe_gex": 0,
      "net_gex": -79299749.22,
      "ce_iv": 17.47,
      "pe_iv": null
    },
    {
      "strike": 25800.0,
      "ce_gex": -476581612.83,
      "pe_gex": 0,
      "net_gex": -476581612.83,
      "ce_iv": 17.77,
      "pe_iv": null
    },
    {
      "strike": 25850.0,
      "ce_gex": -48369344.57,
      "pe_gex": 0,
      "net_gex": -48369344.57,
      "ce_iv": 18.16,
      "pe_iv": null
    },
    {
      "strike": 25900.0,
      "ce_gex": -164349594.18,
      "pe_gex": 0,
      "net_gex": -164349594.18,
      "ce_iv": 18.54,
      "pe_iv": null
    },
    {
      "strike": 25950.0,
      "ce_gex": -38523705.32,
      "pe_gex": 0,
      "net_gex": -38523705.32,
      "ce_iv": 18.9,
      "pe_iv": null
    },
    {
      "strike": 26000.0,
      "ce_gex": -555201962.39,
      "pe_gex": 0,
      "net_gex": -555201962.39,
      "ce_iv": 19.53,
      "pe_iv": null
    },
    {
      "strike": 26050.0,
      "ce_gex": -52965388.6,
      "pe_gex": 0,
      "net_gex": -52965388.6,
      "ce_iv": 19.58,
      "pe_iv": null
    },
    {
      "strike": 26100.0,
      "ce_gex": -141939382.63,
      "pe_gex": 0,
      "net_gex": -141939382.63,
      "ce_iv": 19.89,
      "pe_iv": null
    },
    {
      "strike": 26150.0,
      "ce_gex": -8924265.43,
      "pe_gex": 0,
      "net_gex": -8924265.43,
      "ce_iv": 20.54,
      "pe_iv": null
    },
    {
      "strike": 26200.0,
      "ce_gex": -26139315.64,
      "pe_gex": 0,
      "net_gex": -26139315.64,
      "ce_iv": 21.01,
      "pe_iv": null
    },
    {
      "strike": 26250.0,
      "ce_gex": -5598962.12,
      "pe_gex": 0,
      "net_gex": -5598962.12,
      "ce_iv": 21.49,
      "pe_iv": null
    },
    {
      "strike": 26300.0,
      "ce_gex": -9853143.47,
      "pe_gex": 0,
      "net_gex": -9853143.47,
      "ce_iv": 21.96,
      "pe_iv": null
    },
    {
      "strike": 26350.0,
      "ce_gex": -3292526.89,
      "pe_gex": 0,
      "net_gex": -3292526.89,
      "ce_iv": 22.44,
      "pe_iv": null
    },
    {
      "strike": 26400.0,
      "ce_gex": -5956070.26,
      "pe_gex": 0,
      "net_gex": -5956070.26,
      "ce_iv": 22.91,
      "pe_iv": null
    },
    {
      "strike": 26450.0,
      "ce_gex": -3949951.05,
      "pe_gex": 0,
      "net_gex": -3949951.05,
      "ce_iv": 23.56,
      "pe_iv": null
    },
    {
      "strike": 26500.0,
      "ce_gex": -25926437.68,
      "pe_gex": 0,
      "net_gex": -25926437.68,
      "ce_iv": 23.84,
      "pe_iv": null
    },
    {
      "strike": 26550.0,
      "ce_gex": -11173063.44,
      "pe_gex": 0,
      "net_gex": -11173063.44,
      "ce_iv": 24.31,
      "pe_iv": null
    }
  ]
}